Doxhooks-0.6.0.dist-info/DESCRIPTION.rst
Doxhooks-0.6.0.dist-info/METADATA
Doxhooks-0.6.0.dist-info/RECORD
Doxhooks-0.6.0.dist-info/WHEEL
Doxhooks-0.6.0.dist-info/metadata.json
Doxhooks-0.6.0.dist-info/top_level.txt
Doxhooks-0.6.0.dist-info/zip-safe
doxhooks/__init__.py
doxhooks/console.py
doxhooks/data_stores.py
doxhooks/dataio.py
doxhooks/dependency_databases.py
doxhooks/errors.py
doxhooks/file_domains.py
doxhooks/fileio.py
doxhooks/filetrees.py
doxhooks/fingerprint.py
doxhooks/functions.py
doxhooks/main.py
doxhooks/metaclasses.py
doxhooks/preprocessor_contexts.py
doxhooks/preprocessor_factories.py
doxhooks/preprocessors.py
doxhooks/resource_configs.py
doxhooks/resource_environments.py
doxhooks/resource_factories.py
doxhooks/resources.py
doxhooks/server_configs.py
doxhooks/url_mappings.py
