Metadata-Version: 2.0
Name: Doxhooks
Version: 0.6.0
Summary: Abstract away the content and maintenance of files in your project.
Home-page: https://github.com/nre/doxhooks
Author: Nick Evans
Author-email: nick.evans3976@gmail.com
License: MIT
Keywords: abstract build code document file hook preprocessor project resource source text
Platform: any
Classifier: Development Status :: 4 - Beta
Classifier: Environment :: Console
Classifier: Intended Audience :: Developers
Classifier: License :: OSI Approved :: MIT License
Classifier: Natural Language :: English
Classifier: Operating System :: OS Independent
Classifier: Programming Language :: Python :: 3 :: Only
Classifier: Programming Language :: Python :: 3.3
Classifier: Programming Language :: Python :: 3.4
Classifier: Programming Language :: Python :: 3.5
Classifier: Topic :: Software Development :: Build Tools
Classifier: Topic :: Software Development :: Pre-processors
